__init__.py
fk_recoding.py
EM_transmission-0.0.1.dist-info/LICENSE
EM_transmission-0.0.1.dist-info/METADATA
EM_transmission-0.0.1.dist-info/WHEEL
EM_transmission-0.0.1.dist-info/top_level.txt
EM_transmission-0.0.1.dist-info/RECORD
