Metadata-Version: 2.1
Name: EM-transmission
Version: 0.0.1
Summary: Electric Monitoring system utilizing image sensor
Author-email: Taehoon Koh <thkoh@suncom.co.kr>, Yonghoon Kim <csyhkim@silla.ac.kr>
Project-URL: Homepage, https://suncom.co.kr
Project-URL: Bug Tracker, https://silla.ac.kr
Classifier: Programming Language :: Python :: 3
Classifier: License :: OSI Approved :: MIT License
Classifier: Operating System :: OS Independent
Requires-Python: >=3.9
License-File: LICENSE
